{
  "name": "hyperledger-fabric",
  "displayName": "Hyperledger Fabric on SAP BTP",
  "description": "The Hyperledger Fabric service on SAP BTP lets you provision a Hyperledger Fabric node and join it to a network of nodes. Hyperledger Fabric supports Enterprise ready blockchain with smart contracts.",
  "icon": "https://digitalmarketplace-sapcpprd.s3.eu-central-1.amazonaws.com/11rA5_aU-6481o6j7mrYANBY6mEpKyz2yBRJM8JB_0N4GGvzY2VavIL5K-kfgFln.svg",
  "links": [
    {
      "value": "http://help.sap.com/disclaimer?site=https://open.sap.com/courses/leo4",
      "classification": "learning",
      "type": "Link",
      "text": "OpenSAP: An Introduction to Blockchain",
      "altText": ""
    },
    {
      "value": "https://cloudplatform.sap.com/capabilities/product-info.Hyperledger-Fabric--on-SAP-Cloud-Platform.b9fb18ba-a2dc-485b-ad59-79c30c15ec93.html",
      "classification": "marketing",
      "type": "Link",
      "text": "Learn more about this service and how to purchase it.",
      "altText": ""
    },
    {
      "value": "https://community.sap.com/search/?ct=blog&q=Hyperledger%20Fabric%20on%20SAP%20BTP",
      "classification": "SAP Community Blog Posts",
      "type": "Link",
      "text": "SAP Community Blog Posts",
      "altText": ""
    },
    {
      "value": "https://community.sap.com/search/?ct=qa&q=Hyperledger%20Fabric%20on%20SAP%20BTP",
      "classification": "SAP Community Questions and Answers",
      "type": "Link",
      "text": "SAP Community Questions and Answers",
      "altText": ""
    },
    {
      "value": "https://help.sap.com/doc/43b304f99a8145809c78f292bfc0bc58/Cloud/en-US/98bf747111574187a7c76f8ced51cfeb.html?sel1=Hyperledger%20Fabric",
      "classification": "Documentation",
      "type": "Link",
      "text": "What's New",
      "altText": ""
    },
    {
      "value": "https://help.sap.com/viewer/65de2977205c403bbc107264b8eccf4b/Cloud/en-US/5dd739823b824b539eee47b7860a00be.html",
      "classification": "Support",
      "type": "Link",
      "text": "Support",
      "altText": ""
    },
    {
      "value": "https://help.sap.com/viewer/81f693ad49a046cba506cc9bd51052d0/BLOCKCHAIN/en-US",
      "classification": "Documentation",
      "type": "Link",
      "text": "Developing with Hyperledger Fabric",
      "altText": "Developing with Hyperledger Fabric"
    },
    {
      "value": "https://help.sap.com/viewer/9d945c48156348aabea50a88d4661033/BLOCKCHAIN/en-US",
      "classification": "Documentation",
      "type": "Link",
      "text": "Initial Setup",
      "altText": ""
    },
    {
      "value": "https://help.sap.com/viewer/b45fb6803f784c0496b5ae7cd771e186/BLOCKCHAIN/en-US/0ab5eec6d51845f8849ef78dd6329a2c.html",
      "classification": "Documentation",
      "type": "Link",
      "text": "Provisioning a Node and Building a Hyperledger Fabric Network",
      "altText": "Provisioning a Node and Building a Hyperledger Fabric Network"
    },
    {
      "value": "https://help.sap.com/viewer/b45fb6803f784c0496b5ae7cd771e186/BLOCKCHAIN/en-US/7700dfca1a9f4382823d197347acde87.html",
      "classification": "Documentation",
      "type": "Link",
      "text": "Understanding a Hyperledger Fabric Network",
      "altText": "Understanding a Hyperledger Fabric Network"
    },
    {
      "value": "https://help.sap.com/viewer/b45fb6803f784c0496b5ae7cd771e186/BLOCKCHAIN/en-US/d4456a38676b4c8e94c0588730010bfd.html",
      "classification": "Documentation",
      "type": "Link",
      "text": "Creating and Managing Hyperledger Fabric Channels",
      "altText": ""
    },
    {
      "value": "https://help.sap.com/viewer/p/HYPERLEDGER_FABRIC",
      "classification": "Documentation",
      "type": "Link",
      "text": "Help Portal Product Page",
      "altText": ""
    },
    {
      "value": "https://help.sap.com/viewer/p/HYPERLEDGER_FABRIC/",
      "classification": "Documentation",
      "type": "Link",
      "text": "Documentation",
      "altText": ""
    }
  ],
  "servicePlans": [
    {
      "name": "backbone",
      "displayName": "backbone",
      "category": "SERVICE",
      "description": "Each Hyperledger Fabric network requires exactly one backbone node. This node provisions all Hyperledger Fabric network relevant infrastructure.",
      "isFree": false,
      "dataCenters": [
        {
          "region": "eu10",
          "name": "Europe (Frankfurt)"
        },
        {
          "region": "us10",
          "name": "US East (VA)"
        }
      ],
      "schemas": {
        "service_binding": {
          "create": {
            "parameters": {
              "$schema": "http://json-schema.org/draft-04/schema#",
              "type": "object",
              "properties": {
                "channelId": {
                  "default": "< the channel that should be exported >",
                  "description": "Reverse DNS id of the channel to create the service key for.",
                  "type": "string"
                },
                "comment": {
                  "default": "< user defined comment >",
                  "description": "Comment that describes the created service binding.",
                  "type": "string"
                },
                "transient": {
                  "default": {},
                  "description": "Transient data sent with every request to the node.",
                  "type": "object"
                },
                "permissions": {
                  "default": [],
                  "description": "Permissions for the service binding.",
                  "type": "array"
                }
              }
            }
          }
        }
      }
    },
    {
      "name": "channel",
      "displayName": "channel",
      "category": "SERVICE",
      "description": "Exposes an existing Hyperledger Fabric channel created by the network administrator in a SAP BTP space for using.",
      "isFree": true,
      "dataCenters": [
        {
          "region": "eu10",
          "name": "Europe (Frankfurt)"
        },
        {
          "region": "us10",
          "name": "US East (VA)"
        }
      ],
      "schemas": {
        "service_instance": {
          "create": {
            "parameters": {
              "$schema": "http://json-schema.org/draft-04/schema#",
              "type": "object",
              "properties": {
                "channelId": {
                  "default": "< the channel that should be imported >",
                  "description": "Reverse DNS id of the channel to configure the service instance for.",
                  "type": "string"
                },
                "channelSecret": {
                  "default": "< the channel secret >",
                  "description": "Secret to map the new channel service instance to the corresponding hyperledger channel",
                  "type": "string"
                },
                "comment": {
                  "default": "< user defined comment >",
                  "description": "Comment that describes the created channel service instance.",
                  "type": "string"
                }
              }
            }
          }
        }
      }
    },
    {
      "name": "cyon",
      "displayName": "cyon",
      "category": "SERVICE",
      "description": "Connect Your Own Network (CYON) into the SAP BTP.",
      "isFree": true,
      "dataCenters": [
        {
          "region": "eu10",
          "name": "Europe (Frankfurt)"
        },
        {
          "region": "us10",
          "name": "US East (VA)"
        }
      ],
      "schemas": {
        "service_instance": {
          "create": {
            "parameters": {
              "$schema": "http://json-schema.org/draft-04/schema#",
              "type": "object",
              "properties": {
                "peerOrg": {
                  "default": "< peer org name >",
                  "description": "peer org name",
                  "type": "string"
                },
                "peerAdmin": {
                  "default": {
                    "certificate": "< peer user certificate> ",
                    "key": "< peer user key >"
                  },
                  "description": "peer admin user",
                  "type": "object"
                },
                "peers": {
                  "default": [
                    "< peer url:port >"
                  ],
                  "description": "peer urls",
                  "type": "array"
                },
                "peerTlsCaCertificate": {
                  "default": "< TLS CA certificate of the peer org >",
                  "description": "TLS CA certificate of the peer org",
                  "type": "string"
                },
                "peerCaCertificate": {
                  "default": "< (optional) peer ca certificate >",
                  "description": "peer ca certificate",
                  "type": "string"
                },
                "ordererOrg": {
                  "default": "< (optional) orderer org name >",
                  "description": "orderer org name",
                  "type": "string"
                },
                "ordererAdmin": {
                  "default": {
                    "certificate": "< (optional) orderer user certificate> ",
                    "key": "< (optional) orderer user key >"
                  },
                  "description": "(optional) orderer admin user",
                  "type": "object"
                },
                "orderers": {
                  "default": [
                    "< (optional) orderer url:port >"
                  ],
                  "description": "orderer urls",
                  "type": "array"
                },
                "ordererTlsCaCertificate": {
                  "default": "< TLS CA certificate of the orderer org >",
                  "description": "TLS CA certificate of the orderer org",
                  "type": "string"
                },
                "consortium": {
                  "default": "< name of the consortium >",
                  "description": "name of the consortium",
                  "type": "string"
                },
                "peerCertificateAuthority": {
                  "default": {
                    "certificate": "< (optional) certificate authority certificate> ",
                    "key": "< (optional) certificate authority private key >",
                    "certificateChain": "< (optional) certificate authority certificate chain >"
                  },
                  "description": "(optional) certificate authority of peer admin user",
                  "type": "object"
                }
              }
            }
          }
        },
        "service_binding": {
          "create": {
            "parameters": {
              "$schema": "http://json-schema.org/draft-04/schema#",
              "type": "object",
              "properties": {
                "channelId": {
                  "default": "< the channel that should be exported >",
                  "description": "Reverse DNS id of the channel to create the service key for.",
                  "type": "string"
                },
                "comment": {
                  "default": "< user defined comment >",
                  "description": "Comment that describes the created service binding.",
                  "type": "string"
                },
                "transient": {
                  "default": {},
                  "description": "Transient data sent with every request to the node.",
                  "type": "object"
                },
                "permissions": {
                  "default": [],
                  "description": "Permissions for the service binding.",
                  "type": "array"
                }
              }
            }
          }
        }
      }
    },
    {
      "name": "dev",
      "displayName": "dev",
      "category": "SERVICE",
      "description": "Environment with all relevant APIs for developing and testing of Hyperledger Fabric Chaincode.",
      "isFree": false,
      "dataCenters": [
        {
          "region": "eu10",
          "name": "Europe (Frankfurt)"
        },
        {
          "region": "us10",
          "name": "US East (VA)"
        }
      ],
      "schemas": {
        "service_binding": {
          "create": {
            "parameters": {
              "$schema": "http://json-schema.org/draft-04/schema#",
              "type": "object",
              "properties": {
                "channelId": {
                  "default": "< the channel that should be exported >",
                  "description": "Reverse DNS id of the channel to create the service key for.",
                  "type": "string"
                },
                "comment": {
                  "default": "< user defined comment >",
                  "description": "Comment that describes the created service binding.",
                  "type": "string"
                },
                "transient": {
                  "default": {},
                  "description": "Transient data sent with every request to the node.",
                  "type": "object"
                },
                "permissions": {
                  "default": [],
                  "description": "Permissions for the service binding.",
                  "type": "array"
                }
              }
            }
          }
        }
      }
    },
    {
      "name": "node",
      "displayName": "node",
      "category": "SERVICE",
      "description": "Hyperledger Fabric node that must be joined to a Hyperledger Fabric network for active participation.",
      "isFree": false,
      "dataCenters": [
        {
          "region": "eu10",
          "name": "Europe (Frankfurt)"
        },
        {
          "region": "us10",
          "name": "US East (VA)"
        }
      ],
      "schemas": {
        "service_binding": {
          "create": {
            "parameters": {
              "$schema": "http://json-schema.org/draft-04/schema#",
              "type": "object",
              "properties": {
                "channelId": {
                  "default": "< the channel that should be exported >",
                  "description": "Reverse DNS id of the channel to create the service key for.",
                  "type": "string"
                },
                "comment": {
                  "default": "< user defined comment >",
                  "description": "Comment that describes the created service binding.",
                  "type": "string"
                },
                "transient": {
                  "default": {},
                  "description": "Transient data sent with every request to the node.",
                  "type": "object"
                },
                "permissions": {
                  "default": [],
                  "description": "Permissions for the service binding.",
                  "type": "array"
                }
              }
            }
          }
        }
      }
    },
    {
      "name": "testnet",
      "displayName": "testnet",
      "category": "SERVICE",
      "description": "Hyperledger Fabric node which is part of a cross organizational test network available for developing and testing distributed applications. It may not be used productively.",
      "isFree": false,
      "dataCenters": [
        {
          "region": "eu10",
          "name": "Europe (Frankfurt)"
        },
        {
          "region": "us10",
          "name": "US East (VA)"
        }
      ],
      "schemas": {
        "service_binding": {
          "create": {
            "parameters": {
              "$schema": "http://json-schema.org/draft-04/schema#",
              "type": "object",
              "properties": {
                "channelId": {
                  "default": "< the channel that should be exported >",
                  "description": "Reverse DNS id of the channel to create the service key for.",
                  "type": "string"
                },
                "comment": {
                  "default": "< user defined comment >",
                  "description": "Comment that describes the created service binding.",
                  "type": "string"
                },
                "transient": {
                  "default": {},
                  "description": "Transient data sent with every request to the node.",
                  "type": "object"
                },
                "permissions": {
                  "default": [],
                  "description": "Permissions for the service binding.",
                  "type": "array"
                }
              }
            }
          }
        }
      }
    }
  ]
}