{
  "name": "mdmbusinesspartnerapplication",
  "displayName": "SAP Business Partner Application",
  "description": "SAP Business Partner Application",
  "icon": null,
  "links": [],
  "servicePlans": [
    {
      "name": "saas-application",
      "displayName": "SAP Cloud Platform Master Data Management for business partners",
      "category": "APPLICATION",
      "description": "SAP Cloud Platform Master Data Management for business partners",
      "isFree": false,
      "dataCenters": [
        {
          "region": "eu10",
          "name": "Europe (Frankfurt)"
        },
        {
          "region": "us10",
          "name": "US East (VA)"
        }
      ],
      "schemas": null
    }
  ]
}